icon_getinfo/__init__.py
icon_getinfo/__main__.py
icon_getinfo/__version__.py
icon_getinfo/icon_getinfo_cli.py
icon_getinfo-0.1.3.dist-info/METADATA
icon_getinfo-0.1.3.dist-info/WHEEL
icon_getinfo-0.1.3.dist-info/entry_points.txt
icon_getinfo-0.1.3.dist-info/top_level.txt
icon_getinfo-0.1.3.dist-info/RECORD
