Metadata-Version: 2.1
Name: icon-getinfo
Version: 0.1.3
Summary: Icon Blockchain Network node get information.
Home-page: https://github.com/HonamSong/icon_getinfo
Author: Honam Song
Author-email: hnsong@iconloop.com
License: MIT
Platform: UNKNOWN
Classifier: Programming Language :: Python :: 3
Classifier: License :: OSI Approved :: MIT License
Classifier: Operating System :: OS Independent
Requires-Python: >=3.7
Requires-Dist: urllib3 (>=1.26.8)
Requires-Dist: requests (>=2.27.1)
Requires-Dist: termcolor (>=1.1.0)
Requires-Dist: prettytable (>=3.1.1)
Requires-Dist: numpy (>=1.21.5)
